vector_index_mcp/__init__.py
vector_index_mcp/config.py
vector_index_mcp/content_extractor.py
vector_index_mcp/file_watcher.py
vector_index_mcp/indexer.py
vector_index_mcp/main_mcp.py
vector_index_mcp/mcp_server.py
vector_index_mcp/models.py
vector_index_mcp-3.1.2.dist-info/METADATA
vector_index_mcp-3.1.2.dist-info/WHEEL
vector_index_mcp-3.1.2.dist-info/entry_points.txt
vector_index_mcp-3.1.2.dist-info/top_level.txt
vector_index_mcp-3.1.2.dist-info/RECORD
