Metadata-Version: 2.4
Name: vector-index-mcp
Version: 3.1.2
Summary: MCP Server for Software Project Indexing & Semantic Search
Author-email: Elisei Shchukin <yelis.chuk@gmail.com>
License: MIT
Project-URL: Homepage, https://github.com/synonymouse/vector-index-mcp
Project-URL: Bug Tracker, https://github.com/synonymouse/vector-index-mcp/issues
Classifier: Programming Language :: Python :: 3
Classifier: License :: OSI Approved :: MIT License
Classifier: Operating System :: OS Independent
Classifier: Topic :: Scientific/Engineering :: Artificial Intelligence
Requires-Python: >=3.10
Requires-Dist: watchdog
Requires-Dist: sentence-transformers
Requires-Dist: transformers
Requires-Dist: lancedb
Requires-Dist: python-dotenv
Requires-Dist: pydantic
Requires-Dist: tiktoken
Requires-Dist: pathspec
Requires-Dist: mcp[cli]
Provides-Extra: dev
Requires-Dist: pytest; extra == "dev"
Requires-Dist: pytest-asyncio; extra == "dev"
Requires-Dist: ruff; extra == "dev"
